geotiff_to_wavetable/__init__.py
geotiff_to_wavetable/cli.py
geotiff_to_wavetable/converter.py
geotiff_to_wavetable/io_utils.py
geotiff_to_wavetable/py.typed
geotiff_to_wavetable/validators.py
geotiff_to_wavetable-0.1.1.dist-info/licenses/LICENSE
geotiff_to_wavetable-0.1.1.dist-info/METADATA
geotiff_to_wavetable-0.1.1.dist-info/WHEEL
geotiff_to_wavetable-0.1.1.dist-info/entry_points.txt
geotiff_to_wavetable-0.1.1.dist-info/top_level.txt
geotiff_to_wavetable-0.1.1.dist-info/RECORD
