Metadata-Version: 2.4
Name: geotiff-to-wavetable
Version: 0.1.1
Summary: Convert GeoTIFF elevation data to wavetable files for synthesizers
Author-email: Colby Goettel <colby.goettel@gmail.com>
License: MIT
Project-URL: Homepage, https://gitlab.com/colby.goettel/geotiff-to-wavetable-converter
Project-URL: Repository, https://gitlab.com/colby.goettel/geotiff-to-wavetable-converter
Project-URL: Issues, https://gitlab.com/colby.goettel/geotiff-to-wavetable-converter/-/issues
Keywords: geotiff,wavetable,audio,synthesizer,elevation,terrain
Classifier: Development Status :: 3 - Alpha
Classifier: Intended Audience :: Developers
Classifier: Intended Audience :: End Users/Desktop
Classifier: License :: OSI Approved :: MIT License
Classifier: Programming Language :: Python :: 3
Classifier: Programming Language :: Python :: 3.10
Classifier: Programming Language :: Python :: 3.11
Classifier: Programming Language :: Python :: 3.12
Classifier: Programming Language :: Python :: 3.13
Classifier: Programming Language :: Python :: 3.14
Classifier: Topic :: Multimedia :: Sound/Audio
Classifier: Topic :: Scientific/Engineering :: GIS
Requires-Python: >=3.10
License-File: LICENSE
Requires-Dist: matplotlib>=3.10.1
Requires-Dist: opencv-python>=4.12.0.88
Requires-Dist: rasterio>=1.4.4
Provides-Extra: test
Requires-Dist: mypy>=1.19.1; extra == "test"
Requires-Dist: pre_commit>=4.5.1; extra == "test"
Requires-Dist: pytest>=8.3.2; extra == "test"
Requires-Dist: ruff>=0.14.10; extra == "test"
Dynamic: license-file
